web_maestro/BRIDGE.md
web_maestro/EXAMPLES.md
web_maestro/MIGRATION.md
web_maestro/README.md
web_maestro/__about__.py
web_maestro/__init__.py
web_maestro/browser.py
web_maestro/compatibility.py
web_maestro/context.py
web_maestro/crawl.py
web_maestro/exceptions.py
web_maestro/fetch.py
web_maestro/multi_provider.py
web_maestro/trace_utils.py
web_maestro/agents/__init__.py
web_maestro/agents/scout_bridge.py
web_maestro/capture/__init__.py
web_maestro/config/__init__.py
web_maestro/config/base.py
web_maestro/config/config_classes.py
web_maestro/config/llm_config.py
web_maestro/core/__init__.py
web_maestro/core/browser_setup.py
web_maestro/core/context.py
web_maestro/core/exceptions.py
web_maestro/core/maestro.py
web_maestro/detectors/__init__.py
web_maestro/detectors/element_detector.py
web_maestro/detectors/image_detector.py
web_maestro/detectors/link_detector.py
web_maestro/dom_capture/__init__.py
web_maestro/dom_capture/ai_scout.py
web_maestro/dom_capture/capture.py
web_maestro/dom_capture/click_strategies.py
web_maestro/dom_capture/expansion.py
web_maestro/dom_capture/exploration.py
web_maestro/dom_capture/scroll.py
web_maestro/dom_capture/stability.py
web_maestro/dom_capture/tab_expansion.py
web_maestro/dom_capture/universal_capture.py
web_maestro/domains/__init__.py
web_maestro/domains/domain_config.py
web_maestro/interfaces/__init__.py
web_maestro/interfaces/base.py
web_maestro/models/__init__.py
web_maestro/models/base.py
web_maestro/models/content.py
web_maestro/models/types.py
web_maestro/processors/__init__.py
web_maestro/processors/adapters.py
web_maestro/processors/base.py
web_maestro/processors/html_cleaner.py
web_maestro/processors/multimodal_extractor.py
web_maestro/processors/pdf_processor.py
web_maestro/providers/__init__.py
web_maestro/providers/anthropic.py
web_maestro/providers/base.py
web_maestro/providers/factory.py
web_maestro/providers/ollama.py
web_maestro/providers/openai.py
web_maestro/providers/portkey.py
web_maestro/utils/__init__.py
web_maestro-1.0.0.dist-info/METADATA
web_maestro-1.0.0.dist-info/WHEEL
web_maestro-1.0.0.dist-info/RECORD
