Metadata-Version: 2.4
Name: web-maestro
Version: 1.0.0
Summary: Production-ready web content extraction with multi-provider LLM support and intelligent browser automation
Project-URL: Homepage, https://github.com/fede-dash/web-maestro
Project-URL: Documentation, https://web-maestro.readthedocs.io
Project-URL: Repository, https://github.com/fede-dash/web-maestro.git
Project-URL: Bug Tracker, https://github.com/fede-dash/web-maestro/issues
Author-email: Maestro Team <team@maestro.dev>
Maintainer-email: Maestro Team <team@maestro.dev>
License: MIT
Keywords: ai,anthropic,async,automation,browser-automation,claude,content-extraction,data-extraction,gpt,llm,multi-provider,openai,playwright,streaming,web-crawler,web-scraping
Classifier: Development Status :: 4 - Beta
Classifier: Environment :: Web Environment
Classifier: Intended Audience :: Developers
Classifier: License :: OSI Approved :: MIT License
Classifier: Operating System :: OS Independent
Classifier: Programming Language :: Python :: 3
Classifier: Programming Language :: Python :: 3.9
Classifier: Programming Language :: Python :: 3.10
Classifier: Programming Language :: Python :: 3.11
Classifier: Programming Language :: Python :: 3.12
Classifier: Topic :: Internet :: WWW/HTTP
Classifier: Topic :: Software Development :: Libraries :: Python Modules
Classifier: Topic :: Text Processing
Requires-Python: >=3.9
Requires-Dist: aiohttp>=3.8.0
Requires-Dist: beautifulsoup4>=4.12.0
Requires-Dist: chardet>=5.0.0
Requires-Dist: lxml>=4.9.0
Requires-Dist: pdf2image>=1.16.0
Requires-Dist: pillow>=10.0.0
Requires-Dist: playwright>=1.40.0
Requires-Dist: pydantic>=2.0.0
Requires-Dist: python-dotenv>=1.0.0
Requires-Dist: pyyaml>=6.0.2
Requires-Dist: tenacity>=8.0.0
Requires-Dist: tiktoken>=0.5.0
Provides-Extra: all-features
Requires-Dist: anthropic>=0.8.0; extra == 'all-features'
Requires-Dist: ollama>=0.1.0; extra == 'all-features'
Requires-Dist: openai>=1.0.0; extra == 'all-features'
Requires-Dist: pdf2image>=1.16.0; extra == 'all-features'
Requires-Dist: pdfplumber>=0.9.0; extra == 'all-features'
Requires-Dist: pillow>=10.0.0; extra == 'all-features'
Requires-Dist: portkey-ai>=1.14.0; extra == 'all-features'
Requires-Dist: pypdf2>=3.0.0; extra == 'all-features'
Provides-Extra: all-providers
Requires-Dist: anthropic>=0.8.0; extra == 'all-providers'
Requires-Dist: ollama>=0.1.0; extra == 'all-providers'
Requires-Dist: openai>=1.0.0; extra == 'all-providers'
Requires-Dist: portkey-ai>=1.14.0; extra == 'all-providers'
Provides-Extra: anthropic
Requires-Dist: anthropic>=0.8.0; extra == 'anthropic'
Provides-Extra: dev
Requires-Dist: black>=23.0.0; extra == 'dev'
Requires-Dist: mypy>=1.0.0; extra == 'dev'
Requires-Dist: pre-commit>=3.0.0; extra == 'dev'
Requires-Dist: pytest-asyncio>=0.21.0; extra == 'dev'
Requires-Dist: pytest-cov>=4.0.0; extra == 'dev'
Requires-Dist: pytest-mock>=3.10.0; extra == 'dev'
Requires-Dist: pytest>=7.0.0; extra == 'dev'
Requires-Dist: ruff>=0.1.6; extra == 'dev'
Requires-Dist: types-beautifulsoup4; extra == 'dev'
Requires-Dist: types-lxml; extra == 'dev'
Requires-Dist: types-pyyaml; extra == 'dev'
Provides-Extra: multimodal
Requires-Dist: pdf2image>=1.16.0; extra == 'multimodal'
Requires-Dist: pillow>=10.0.0; extra == 'multimodal'
Provides-Extra: ollama
Requires-Dist: ollama>=0.1.0; extra == 'ollama'
Provides-Extra: openai
Requires-Dist: openai>=1.0.0; extra == 'openai'
Provides-Extra: pdf
Requires-Dist: pdf2image>=1.16.0; extra == 'pdf'
Requires-Dist: pdfplumber>=0.9.0; extra == 'pdf'
Requires-Dist: pillow>=10.0.0; extra == 'pdf'
Requires-Dist: pypdf2>=3.0.0; extra == 'pdf'
Provides-Extra: portkey
Requires-Dist: portkey-ai>=1.14.0; extra == 'portkey'
